sap_ecs_azure_log_forwarder/__init__.py
sap_ecs_azure_log_forwarder/config.py
sap_ecs_azure_log_forwarder/log_processor.py
sap_ecs_azure_log_forwarder/message_processing.py
sap_ecs_azure_log_forwarder/queue_consumer.py
sap_ecs_azure_log_forwarder-1.1.1.dist-info/LICENSE
sap_ecs_azure_log_forwarder-1.1.1.dist-info/METADATA
sap_ecs_azure_log_forwarder-1.1.1.dist-info/WHEEL
sap_ecs_azure_log_forwarder-1.1.1.dist-info/entry_points.txt
sap_ecs_azure_log_forwarder-1.1.1.dist-info/RECORD
